activation_code.py
base32check1.py
base32check1-0.2.0.dist-info/LICENSE
base32check1-0.2.0.dist-info/METADATA
base32check1-0.2.0.dist-info/WHEEL
base32check1-0.2.0.dist-info/top_level.txt
base32check1-0.2.0.dist-info/zip-safe
base32check1-0.2.0.dist-info/RECORD
