Metadata-Version: 2.1
Name: base32check1
Version: 0.2.0
Summary: Implementation of the base32check1 algorithm.
Home-page: https://github.com/bitmarck-service/base32check-python
Author: BITMARCK Service GmbH
Author-email: info@bitmarck.de
License: Apache v2
Project-URL: Homepage, https://base32check.org/
Project-URL: Source, https://github.com/bitmarck-service/base32check-python
Keywords: base32,RFC 4648
Platform: unix
Platform: linux
Platform: osx
Platform: cygwin
Platform: win32
Classifier: Development Status :: 4 - Beta
Classifier: Intended Audience :: Developers
Classifier: License :: OSI Approved :: Apache Software License
Classifier: Operating System :: MacOS :: MacOS X
Classifier: Operating System :: Microsoft :: Windows
Classifier: Operating System :: POSIX
Classifier: Programming Language :: Python :: 3
Classifier: Programming Language :: Python :: 3 :: Only
Classifier: Programming Language :: Python :: 3.6
Classifier: Programming Language :: Python :: 3.7
Classifier: Programming Language :: Python :: 3.8
Classifier: Programming Language :: Python :: 3.9
Classifier: Topic :: Software Development :: Libraries
Classifier: Topic :: Utilities
Requires-Python: >=3.6
License-File: LICENSE
